{
  "question_number": 7,
  "question_type": "OpenEnded",
  "statement": "Classifique o uso do pronome apassivador “se” no seguinte trecho:",
  "support_text": "“A mãe, então, se afligia: roía o dedo e deixava a unha intacta.” (1º parágrafo)\n“Cada vez mais fria, a moça brinca, se aquece na torreira do sol.” (21º parágrafo)\n“Clareou a voz, para melhor se autorizar.” (12º parágrafo)\n“É o caso se vai seguindo, estória sem história.” (22º parágrafo)\n“Não se vislumbravam sinais dessa derradeiraigem.” (27º parágrafo)",
  "alternatives": [],
  "images": []
}